funk/__init__.py
funk/cli.py
funk/funk.py
funk_cli-0.1.1.dist-info/AUTHORS.rst
funk_cli-0.1.1.dist-info/LICENSE
funk_cli-0.1.1.dist-info/METADATA
funk_cli-0.1.1.dist-info/WHEEL
funk_cli-0.1.1.dist-info/entry_points.txt
funk_cli-0.1.1.dist-info/top_level.txt
funk_cli-0.1.1.dist-info/RECORD
