Metadata-Version: 2.1
Name: funk-cli
Version: 0.1.1
Summary: Turbodrive Terraform
Home-page: https://github.com/leg100/funk
Author: Louis Garman
Author-email: louisgarman@gmail.com
License: MIT license
Keywords: funk
Platform: UNKNOWN
Classifier: Development Status :: 2 - Pre-Alpha
Classifier: Intended Audience :: Developers
Classifier: License :: OSI Approved :: MIT License
Classifier: Natural Language :: English
Classifier: Programming Language :: Python :: 2
Classifier: Programming Language :: Python :: 2.7
Classifier: Programming Language :: Python :: 3
Classifier: Programming Language :: Python :: 3.5
Classifier: Programming Language :: Python :: 3.6
Classifier: Programming Language :: Python :: 3.7
Requires-Python: >=2.7, !=3.0.*, !=3.1.*, !=3.2.*, !=3.3.*, !=3.4.*
Requires-Dist: Click (>=7.0)
